CHANGES.txt
MANIFEST.in
README.rst
setup.py
isotoma/__init__.py
isotoma.plone.defang.egg-info/PKG-INFO
isotoma.plone.defang.egg-info/SOURCES.txt
isotoma.plone.defang.egg-info/dependency_links.txt
isotoma.plone.defang.egg-info/entry_points.txt
isotoma.plone.defang.egg-info/namespace_packages.txt
isotoma.plone.defang.egg-info/not-zip-safe
isotoma.plone.defang.egg-info/requires.txt
isotoma.plone.defang.egg-info/top_level.txt
isotoma/plone/__init__.py
isotoma/plone/defang/__init__.py
isotoma/plone/defang/defang.py
isotoma/plone/defang/fangs.py
isotoma/plone/defang/util.py