Metadata-Version: 1.0
Name: isotoma.plone.defang
Version: 1.0.2
Summary: modify ZODBs for environment migration
Home-page: UNKNOWN
Author: Doug Winter
Author-email: doug.winter@isotoma.com
License: UNKNOWN
Platform: UNKNOWN
Classifier: Framework :: Buildout
Classifier: Intended Audience :: System Administrators
Classifier: Operating System :: POSIX
Classifier: License :: OSI Approved :: Apache Software License
